pala/__init__.py
pala/analysis.py
PALA-0.1.0.dist-info/LICENSE
PALA-0.1.0.dist-info/METADATA
PALA-0.1.0.dist-info/WHEEL
PALA-0.1.0.dist-info/top_level.txt
PALA-0.1.0.dist-info/RECORD
