Metadata-Version: 2.2
Name: PALA
Version: 0.1.0
Summary: Python Audio Loudness Analysis
Home-page: https://github.com/HBB-ThinkTank/PALA
Author: "HBB-ThinkTank"
Author-email: HBB-ThinkTank <your-email@example.com>
License: MIT
Project-URL: Homepage, https://github.com/HBB-ThinkTank/PALA
Project-URL: Repository, https://github.com/HBB-ThinkTank/PALA
Classifier: Programming Language :: Python :: 3
Classifier: License :: OSI Approved :: MIT License
Classifier: Operating System :: OS Independent
Requires-Python: >=3.7
License-File: LICENSE
